README.md
setup.py
xmutant/alarm.py
xmutant/config.py
xmutant/cov.py
xmutant/fn.py
xmutant/logger.py
xmutant/mpool.py
xmutant/mu.py
xmutant/mutants.py
xmutant/mutator.py
xmutant/samplespace.py
xmutant/tests.py
xmutant/typ.py
xmutant/xmutant.py
xmutant.egg-info/PKG-INFO
xmutant.egg-info/SOURCES.txt
xmutant.egg-info/dependency_links.txt
xmutant.egg-info/not-zip-safe
xmutant.egg-info/top_level.txt