Metadata-Version: 1.1
Name: xmutant
Version: 0.3
Summary: The python3 bytecode based mutation analysis framework
Home-page: http://github.com/vrthra/xmutant.py
Author: Rahul Gopinath
Author-email: rahul@gopinath.org
License: GPLv3
Keywords: mutation-testing mutation-analysis
Platform: UNKNOWN
Classifier: Development Status :: 4 - Beta
Classifier: Environment :: Console
Classifier: Intended Audience :: Developers
Classifier: License :: OSI Approved :: GNU General Public License v3 (GPLv3)
Classifier: Operating System :: OS Independent
Classifier: Programming Language :: Python :: 2
Classifier: Topic :: Software Development
Classifier: Topic :: Software Development :: Libraries :: Python Modules
Classifier: Topic :: Software Development :: Testing
